RegionParser/Parser.py
RegionParser/Parser.pyi
RegionParser/__init__.py
RegionParser-1.1.dist-info/LICENSE
RegionParser-1.1.dist-info/METADATA
RegionParser-1.1.dist-info/WHEEL
RegionParser-1.1.dist-info/top_level.txt
RegionParser-1.1.dist-info/RECORD
