Metadata-Version: 2.1
Name: RegionParser
Version: 1.1
Summary: Tools for region parameters parsing
Author: zys
Classifier: Programming Language :: Python :: 3
Classifier: License :: OSI Approved :: MIT License
Classifier: Operating System :: OS Independent
Requires-Python: >=3.6
License-File: LICENSE
Requires-Dist: torch
